2_homework/segment/segment.v
module seg(
     sin,
     seg
    );
     
     input [3:0] sin;
     output [8:0] seg;
     reg [8:0] seg;

    always @(*)
    begin
        case (sin) 
            4'b0000 : seg = 8'b11111100;
            4'b0001 : seg = 8'b01100000;
            4'b0010 : seg = 8'b11011010;
            4'b0011 : seg = 8'b11110010;
            4'b0100 : seg = 8'b01100110;
            4'b0101 : seg = 8'b10110110;
            4'b0110 : seg = 8'b10111110;
            4'b0111 : seg = 8'b11100000;
            4'b1000 : seg = 8'b11111110;
            4'b1001 : seg = 8'b11110110;
            default : seg = 8'b00000000; 
        endcase
    end
    
endmodule

2_homework/segment/tb_segment.v
module tb_seg;

    reg [3:0] t_sin;
    wire [8:0] t_seg;
    integer i;

    seg s0 (
        .sin(t_sin), 
        .seg(t_seg)
    );

    initial begin
    $dumpfile("testbench.vcd"); $dumpvars; 


    #5 t_sin = 4'b0000;

        for(i = 0;i < 16;i = i+1) //run loop for 0 to 15.
        begin
            #5 t_sin = t_sin + 4'b0001;
        end     
    end
      
endmodule

2_homework/segment/testbench.vcd
$date
	Fri Apr 10 19:32:10 2020
$end
$version
	Icarus Verilog
$end
$timescale
	1s
$end
$scope module tb_seg $end
$var wire 9 ! t_seg [8:0] $end
$var reg 4 " t_sin [3:0] $end
$var integer 32 # i [31:0] $end
$scope module s0 $end
$var wire 4 $ sin [3:0] $end
$var reg 9 % seg [8:0] $end
$upscope $end
$upscope $end
$enddefinitions $end
#0
$dumpvars
bx %
bx $
bx #
bx "
bx !
$end
#5
b11111100 !
b11111100 %
b0 #
b0 "
b0 $
#10
b1100000 !
b1100000 %
b1 #
b1 "
b1 $
#15
b11011010 !
b11011010 %
b10 #
b10 "
b10 $
#20
b11110010 !
b11110010 %
b11 #
b11 "
b11 $
#25
b1100110 !
b1100110 %
b100 #
b100 "
b100 $
#30
b10110110 !
b10110110 %
b101 #
b101 "
b101 $
#35
b10111110 !
b10111110 %
b110 #
b110 "
b110 $
#40
b11100000 !
b11100000 %
b111 #
b111 "
b111 $
#45
b11111110 !
b11111110 %
b1000 #
b1000 "
b1000 $
#50
b11110110 !
b11110110 %
b1001 #
b1001 "
b1001 $
#55
b0 !
b0 %
b1010 #
b1010 "
b1010 $
#60
b1011 #
b1011 "
b1011 $
#65
b1100 #
b1100 "
b1100 $
#70
b1101 #
b1101 "
b1101 $
#75
b1110 #
b1110 "
b1110 $
#80
b1111 #
b1111 "
b1111 $
#85
b11111100 !
b11111100 %
b10000 #
b0 "
b0 $
